python_depends/__init__.py
python_depends/depends.py
python_depends/utils.py
depends_python-0.0.1.dist-info/METADATA
depends_python-0.0.1.dist-info/WHEEL
depends_python-0.0.1.dist-info/licenses/LICENSE
depends_python-0.0.1.dist-info/RECORD
