Metadata-Version: 2.4
Name: depends_python
Version: 0.0.1
Summary: Dependency injection for python functions
Project-URL: Source, https://github.com/zayycev22/python_depends
Author: zayycev22
License-File: LICENSE
Classifier: License :: OSI Approved :: MIT License
Classifier: Operating System :: OS Independent
Classifier: Programming Language :: Python :: 3 :: Only
Classifier: Programming Language :: Python :: 3.11
Classifier: Programming Language :: Python :: 3.12
Requires-Python: >=3.11
